nsfwrecog/__init__.py
nsfwrecog/nsfwrecog.py
nsfwrecog-1.0.dist-info/LICENSE
nsfwrecog-1.0.dist-info/METADATA
nsfwrecog-1.0.dist-info/WHEEL
nsfwrecog-1.0.dist-info/top_level.txt
nsfwrecog-1.0.dist-info/RECORD
